{"version":"2.2.1","objects":[{"type":"image","version":"2.2.1","originX":"left","originY":"top","left":-45,"top":-40,"width":960,"height":960,"fill":"rgb(0,0,0)","stroke":null,"strokeWidth":0,"strokeDashArray":null,"strokeLineCap":"butt","strokeLineJoin":"miter","strokeMiterLimit":10,"scaleX":0.5,"scaleY":0.5,"angle":0,"flipX":false,"flipY":false,"opacity":1,"shadow":null,"visible":true,"clipTo":null,"backgroundColor":"","fillRule":"nonzero","paintFirst":"fill","globalCompositeOperation":"source-over","transformMatrix":null,"skewX":0,"skewY":0,"crossOrigin":"","cropX":0,"cropY":0,"lockMovementX":true,"lockMovementY":true,"lockRotation":false,"lockScalingX":false,"lockScalingY":false,"hoverCursor":"default","evented":false,"hasControls":false,"hasBorders":false,"selectable":false,"transparentCorners":true,"src":"http://localhost/greetstore-php/images/product/mobile-cover/Apple-Iphone-8/pixel.png","filters":[]},{"type":"image","version":"2.2.1","originX":"left","originY":"top","left":134,"top":120,"width":6000,"height":4000,"fill":"rgb(0,0,0)","stroke":null,"strokeWidth":0,"strokeDashArray":null,"strokeLineCap":"butt","strokeLineJoin":"miter","strokeMiterLimit":10,"scaleX":0.01,"scaleY":0.01,"angle":0,"flipX":false,"flipY":false,"opacity":1,"shadow":null,"visible":true,"clipTo":null,"backgroundColor":"","fillRule":"nonzero","paintFirst":"fill","globalCompositeOperation":"source-over","transformMatrix":null,"skewX":0,"skewY":0,"crossOrigin":"","cropX":0,"cropY":0,"lockMovementX":false,"lockMovementY":false,"lockRotation":false,"lockScalingX":false,"lockScalingY":false,"hoverCursor":null,"evented":true,"hasControls":true,"hasBorders":true,"selectable":true,"transparentCorners":true,"src":"http://localhost/greetstore-php/uploads/delete_Order-1/1/customization/ai-codes-coding-97077.jpg","filters":[]}],"hoverCursor":"move","width":375,"height":672}